model/_BaseThread.py
model/__init__.py
util/_IsoFormatter.py
util/_Logger.py
util/__init__.py
nascorp.library-0.1.1.dist-info/METADATA
nascorp.library-0.1.1.dist-info/WHEEL
nascorp.library-0.1.1.dist-info/top_level.txt
nascorp.library-0.1.1.dist-info/RECORD
