Metadata-Version: 2.1
Name: nascorp.library
Version: 0.1.1
Summary: Nascorp Library
Home-page: UNKNOWN
Author: NASCORP TECHNOLOGY
License: UNKNOWN
Platform: UNKNOWN
Requires-Python: >=3.6
